Metadata-Version: 1.1
Name: openlmi-scripts-hardware
Version: 0.2.8
Summary: Hardware information available in OpenLMI hardware providers
Home-page: https://github.com/openlmi/openlmi-hardware
Author: Peter Schiffer
Author-email: pschiffe@redhat.com
License: BSD
Download-URL: https://github.com/openlmi/openlmi-hardware/tarball/master
Platform: Any
Classifier: License :: OSI Approved :: BSD License
Classifier: Operating System :: POSIX :: Linux
Classifier: Topic :: System :: Systems Administration
Classifier: Programming Language :: Python
Classifier: Programming Language :: Python :: 2
Classifier: Programming Language :: Python :: 2.7
Classifier: Intended Audience :: Developers
Classifier: Environment :: Console
